[ {
  "alias" : "Click to return to Automation-_1",
  "parameter" : null,
  "parametervalue" : null,
  "type" : null,
  "objectList" : null,
  "attributes" : { },
  "oldValue" : null,
  "status" : null,
  "isFormObject" : false,
  "defaultDataFile" : null,
  "autoAwareObjectType" : null,
  "allowedCharacters" : "",
  "fieldLength" : 0
}, {
  "alias" : "Forgot Password",
  "parameter" : null,
  "parametervalue" : null,
  "type" : null,
  "objectList" : null,
  "attributes" : { },
  "oldValue" : null,
  "status" : null,
  "isFormObject" : false,
  "defaultDataFile" : null,
  "autoAwareObjectType" : null,
  "allowedCharacters" : "",
  "fieldLength" : 0
}, {
  "alias" : "Sign up here",
  "parameter" : null,
  "parametervalue" : null,
  "type" : null,
  "objectList" : null,
  "attributes" : { },
  "oldValue" : null,
  "status" : null,
  "isFormObject" : false,
  "defaultDataFile" : null,
  "autoAwareObjectType" : null,
  "allowedCharacters" : "",
  "fieldLength" : 0
}, {
  "alias" : "TIECHE Inc",
  "parameter" : null,
  "parametervalue" : null,
  "type" : null,
  "objectList" : null,
  "attributes" : { },
  "oldValue" : null,
  "status" : null,
  "isFormObject" : false,
  "defaultDataFile" : null,
  "autoAwareObjectType" : null,
  "allowedCharacters" : "",
  "fieldLength" : 0
} ]